LICENSE
README.md
setup.cfg
setup.py
mcextract/__init__.py
mcextract/__main__.py
mcextract/cli.py
mcextract.egg-info/PKG-INFO
mcextract.egg-info/SOURCES.txt
mcextract.egg-info/dependency_links.txt
mcextract.egg-info/entry_points.txt
mcextract.egg-info/not-zip-safe
mcextract.egg-info/requires.txt
mcextract.egg-info/top_level.txt
tests/test_extract.py
tests/test_extract_cli.py
tests/test_generate.py
tests/test_generate_cli.py
tests/test_map.py
tests/test_map_cli.py