Metadata-Version: 2.1
Name: mcextract
Version: 1.2.0
Summary: Extract assets and data from the Minecraft jar.
Home-page: https://github.com/legopitstop/mcextract/
Author: Legopitstop
Author-email: contact@lpsmods.dev
License: MIT
Keywords: Minecraft,java,jar,assets,data,reports,UserFolder,ServerJars
Classifier: Development Status :: 4 - Beta
Classifier: Intended Audience :: Developers
Classifier: License :: OSI Approved :: MIT License
Classifier: Programming Language :: Python :: 3.11
Requires-Python: >=3.10
License-File: LICENSE
